Metadata-Version: 1.1
Name: impulsare-config
Version: 1.0b5
Summary: A config reader (yaml) that validates config files content.
Home-page: https://github.com/impulsare/config
Author: Emmanuel Dyan
Author-email: emmanuel@impulsare.io
License: AGPLv3
Download-URL: https://github.com/impulsare/config/tarball/1.0b5
Keywords: config,python,yaml
Platform: UNKNOWN
Classifier: Development Status :: 4 - Beta
Classifier: Intended Audience :: Developers
Classifier: Intended Audience :: Information Technology
Classifier: Intended Audience :: Science/Research
Classifier: Intended Audience :: System Administrators
Classifier: License :: OSI Approved :: GNU Affero General Public License v3 or later (AGPLv3+)
Classifier: Programming Language :: Python :: 3.3
Classifier: Programming Language :: Python :: 3.4
Classifier: Programming Language :: Python :: 3.5
Classifier: Programming Language :: Python :: 3.6
Classifier: Topic :: Scientific/Engineering
Classifier: Topic :: System :: Distributed Computing
Classifier: Topic :: System :: Systems Administration
